phisuite/schema/__init__.py
phisuite/schema/common_pb2.py
phisuite/schema/common_pb2_grpc.py
phisuite/schema/entity_pb2.py
phisuite/schema/entity_pb2_grpc.py
phisuite/schema/event_pb2.py
phisuite/schema/event_pb2_grpc.py
phisuite/schema/process_pb2.py
phisuite/schema/process_pb2_grpc.py
phisuite.schema-0.0.2.dist-info/LICENSE
phisuite.schema-0.0.2.dist-info/METADATA
phisuite.schema-0.0.2.dist-info/WHEEL
phisuite.schema-0.0.2.dist-info/top_level.txt
phisuite.schema-0.0.2.dist-info/RECORD
