Metadata-Version: 2.1
Name: phisuite.schema
Version: 0.0.2
Summary: Phi Suite Schema
Home-page: https://github.com/phisuite/schema.py
Author: Phi Skills
Author-email: phisuite@phiskills.com
License: GNU GPLv3
Project-URL: Project website, https://phisuite.com
Project-URL: Company website, https://phiskills.com
Project-URL: Documentation, https://phisuite.com/doc
Project-URL: Source, https://github.com/phisuite/schema.py
Keywords: Phi Suite Data Engineering
Platform: UNKNOWN
Classifier: Development Status :: 2 - Pre-Alpha
Classifier: Intended Audience :: Developers
Classifier: License :: OSI Approved :: GNU General Public License v3 (GPLv3)
Classifier: Programming Language :: Python :: 3
Classifier: Topic :: Software Development
Requires-Python: >=3.8, <4
Requires-Dist: protobuf
Requires-Dist: grpcio
